birdsql
