Metadata-Version: 1.1
Name: birdsql
Version: 0.6.4
Summary: Very simple and basic MySQL speaking objects for python
Home-page: https://pypi.python.org/pypi/birdsql
Author: Anthony Casagrande
Author-email: birdapi@gmail.com
License: MIT
Keywords: mysql birdapi sql orm
Platform: UNKNOWN
Classifier: Development Status :: 4 - Beta
Classifier: Topic :: Database
Classifier: Programming Language :: Python :: 2.7
Classifier: License :: OSI Approved :: MIT License
